{
  "title": "Visualization",
  "icon": "BarChart3",
  "color": "bg-pink-500",
  "description": "Create compelling data visualizations",
  "subcategories": {
    "power-bi": {
      "title": "Power BI",
      "icon": "BarChart3",
      "color": "bg-amber-500",
      "topics": [
        {
          "id": "yoy-growth-powerbi-dax",
          "metaTitle": "Year-over-Year Growth in Power BI DAX: Complete Beginner's Guide (2025) | Ivy Professional School",
          "title": "How to Calculate Year-over-Year Growth in Power BI Using DAX",
          "description": "Master YoY calculations in Power BI with step-by-step DAX formulas. Perfect for beginners and data analysts.",
          "duration": "12 min read",
          "date": "March 6, 2026",
          "content": {
            "hero": {
              "title": "How to Calculate Year-over-Year Growth in Power BI Using DAX",
              "author": "Power BI Expert",
              "date": "March 6, 2026",
              "readTime": "12 min read"
            },
            "sections": [
              {
                "id": "what-is-yoy",
                "title": "What is Year-over-Year (YoY) Growth?",
                "content": [
                  {
                    "type": "paragraph",
                    "text": "<strong>Year-over-Year (YoY) growth</strong> measures how a metric (like revenue, sales, or profit) has changed compared to the same period in the previous year. It is one of the most widely used business performance indicators because it removes the effect of seasonality.",
                    "hasBar": true
                  },
                  {
                    "type": "paragraph",
                    "text": "The formula in plain English:"
                  },
                  {
                    "type": "code",
                    "title": "YoY Formula",
                    "language": "dax",
                    "code": "YoY Growth % = (This Year Value - Last Year Value) / Last Year Value * 100\n\nExample: (96L - 80L) / 80L * 100 = 20% Growth",
                    "borderColor": "amber"
                  }
                ]
              },
              {
                "id": "why-powerbi",
                "title": "Why Calculate YoY in Power BI?",
                "content": [
                  {
                    "type": "paragraph",
                    "text": "Power BI's DAX (Data Analysis Expressions) language includes powerful <strong>time intelligence functions</strong> that automate YoY calculations across your entire dataset — with no manual filtering required. Here's why business analysts love it:"
                  },
                  {
                    "type": "list",
                    "items": [
                      "Dynamic: Automatically updates as new data flows in",
                      "Interactive: Works with slicers and filters instantly",
                      "Visual: Integrates seamlessly with line charts, bar charts, and KPI cards",
                      "Fast: Calculates across millions of rows in seconds"
                    ]
                  },
                  {
                    "type": "callout",
                    "variant": "info",
                    "icon": "💡",
                    "title": "Who needs this?",
                    "content": "Sales analysts, finance teams, marketing managers, operations leads — anyone who needs to track performance trends over time in a business dashboard."
                  }
                ]
              },
              {
                "id": "prerequisites",
                "title": "Prerequisites: Setting Up Your Date Table",
                "content": [
                  {
                    "type": "paragraph",
                    "text": "Before writing any DAX formula, you <strong>must have a proper Date Table</strong> in your Power BI model. Time intelligence functions won't work without one. Here's how to create it in 3 steps:"
                  },
                  {
                    "type": "steps",
                    "items": [
                      {
                        "title": "Open Power BI Desktop and click New Table in the Modeling tab",
                        "description": "This creates a calculated table using DAX. You'll type the formula directly into the formula bar."
                      },
                      {
                        "title": "Paste this DAX formula to generate a complete Date Table",
                        "description": "This creates a continuous calendar from 2020 to 2025 with Year, Quarter, Month, and Day columns."
                      },
                      {
                        "title": "Mark it as the official Date Table",
                        "description": "Right-click the table → Mark as Date Table → select the Date column. This activates all time intelligence functions."
                      }
                    ]
                  },
                  {
                    "type": "code",
                    "title": "DAX — Date Table",
                    "language": "dax",
                    "code": "DateTable =\nADDCOLUMNS(\n    CALENDAR(DATE(2020,1,1), DATE(2025,12,31)),\n    \"Year\",        YEAR([Date]),\n    \"MonthNumber\", MONTH([Date]),\n    \"MonthName\",   FORMAT([Date], \"MMMM\"),\n    \"Quarter\",     \"Q\" & QUARTER([Date]),\n    \"WeekDay\",     FORMAT([Date], \"dddd\")\n)",
                    "borderColor": "blue"
                  },
                  {
                    "type": "callout",
                    "variant": "tip",
                    "icon": "✅",
                    "title": "Pro Tip:",
                    "content": "Your Date Table must be continuous (no gaps). Use CALENDAR() or CALENDARAUTO() — never manually type dates. Also ensure the Date column is set to Date data type, not Text."
                  }
                ]
              },
              {
                "id": "method1",
                "title": "Method 1: SAMEPERIODLASTYEAR (Easiest for Beginners)",
                "phase": "Method 1",
                "content": [
                  {
                    "type": "paragraph",
                    "text": "SAMEPERIODLASTYEAR is the most beginner-friendly time intelligence function in DAX. It shifts the entire date context back exactly one year, so you can compare current and previous year values effortlessly."
                  },
                  {
                    "type": "subtitle",
                    "text": "Step-by-Step: Create the YoY Measure"
                  },
                  {
                    "type": "steps",
                    "items": [
                      {
                        "title": "Create a base measure for Total Sales",
                        "description": "Go to Modeling → New Measure. Type this formula in the formula bar and press Enter."
                      }
                    ]
                  },
                  {
                    "type": "code",
                    "title": "DAX — Base Measure",
                    "language": "dax",
                    "code": "Total Sales = SUM(SalesData[Revenue])",
                    "borderColor": "blue"
                  },
                  {
                    "type": "steps",
                    "items": [
                      {
                        "title": "Create the Previous Year Sales measure",
                        "description": "Create a new measure named PY Sales. This uses CALCULATE to override the date filter context with last year's dates."
                      }
                    ]
                  },
                  {
                    "type": "code",
                    "title": "DAX — SAMEPERIODLASTYEAR",
                    "language": "dax",
                    "code": "PY Sales =\nCALCULATE(\n    [Total Sales],\n    SAMEPERIODLASTYEAR(DateTable[Date])\n)",
                    "borderColor": "blue"
                  },
                  {
                    "type": "callout",
                    "variant": "info",
                    "icon": "🧠",
                    "title": "How it works:",
                    "content": "SAMEPERIODLASTYEAR takes whatever time period is currently visible (e.g., Jan–Mar 2024) and returns the same period from the prior year (Jan–Mar 2023). CALCULATE then evaluates Total Sales within that shifted context."
                  },
                  {
                    "type": "steps",
                    "items": [
                      {
                        "title": "Create the YoY Growth % measure",
                        "description": "Now combine both measures to calculate the actual growth percentage. The IF check prevents division-by-zero errors when prior year data is missing."
                      }
                    ]
                  },
                  {
                    "type": "code",
                    "title": "DAX — YoY Growth %",
                    "language": "dax",
                    "code": "YoY Growth % =\nVAR CY = [Total Sales]\nVAR PY = [PY Sales]\nRETURN\n    IF(\n        PY <> 0 && PY <> BLANK(),\n        DIVIDE(CY - PY, PY),\n        BLANK()\n    )",
                    "borderColor": "amber"
                  }
                ]
              },
              {
                "id": "method2",
                "title": "Method 2: DATEADD Function (More Flexible)",
                "phase": "Method 2",
                "content": [
                  {
                    "type": "paragraph",
                    "text": "DATEADD lets you shift dates by any interval — days, months, quarters, or years. It's more powerful than SAMEPERIODLASTYEAR because you can use it for quarter-over-quarter or month-over-month comparisons too."
                  },
                  {
                    "type": "code",
                    "title": "DAX — DATEADD (Previous Year)",
                    "language": "dax",
                    "code": "PY Sales (DATEADD) =\nCALCULATE(\n    [Total Sales],\n    DATEADD(DateTable[Date], -1, YEAR)\n)\n\n-- To get previous QUARTER instead:\nPQ Sales = CALCULATE([Total Sales], DATEADD(DateTable[Date], -1, QUARTER))\n\n-- To get previous MONTH:\nPM Sales = CALCULATE([Total Sales], DATEADD(DateTable[Date], -1, MONTH))",
                    "borderColor": "blue"
                  },
                  {
                    "type": "callout",
                    "variant": "warn",
                    "icon": "⚠️",
                    "title": "Important:",
                    "content": "DATEADD with -1 YEAR behaves identically to SAMEPERIODLASTYEAR for most scenarios. Use DATEADD when you need intervals other than one year, or when working with partial periods."
                  }
                ]
              },
              {
                "id": "method3",
                "title": "Method 3: PREVIOUSYEAR Function",
                "phase": "Method 3",
                "content": [
                  {
                    "type": "paragraph",
                    "text": "PREVIOUSYEAR returns all dates in the entire preceding year, regardless of the current selection. It's best used when you want the <strong>full previous calendar year</strong> total."
                  },
                  {
                    "type": "code",
                    "title": "DAX — PREVIOUSYEAR",
                    "language": "dax",
                    "code": "PY Sales (PREVIOUSYEAR) =\nCALCULATE(\n    [Total Sales],\n    PREVIOUSYEAR(DateTable[Date])\n)\n\n-- For a fiscal year ending on 31 March:\nFY Previous Year =\nCALCULATE(\n    [Total Sales],\n    PREVIOUSYEAR(DateTable[Date], \"03-31\")\n)",
                    "borderColor": "blue"
                  }
                ]
              },
              {
                "id": "yoy-percent",
                "title": "Calculating YoY Growth Percentage (Best Practice)",
                "phase": "Best Practice",
                "content": [
                  {
                    "type": "paragraph",
                    "text": "Here is the production-ready, error-safe DAX measure for YoY Growth % that handles all edge cases:"
                  },
                  {
                    "type": "code",
                    "title": "DAX — Production-Ready YoY %",
                    "language": "dax",
                    "code": "YoY Growth % =\nVAR CurrentYearSales  = [Total Sales]\nVAR PreviousYearSales =\n    CALCULATE(\n        [Total Sales],\n        SAMEPERIODLASTYEAR(DateTable[Date])\n    )\nRETURN\n    IF(\n        AND(PreviousYearSales <> 0, NOT(ISBLANK(PreviousYearSales))),\n        DIVIDE(\n            CurrentYearSales - PreviousYearSales,\n            PreviousYearSales\n        ),\n        BLANK()\n    )",
                    "borderColor": "amber"
                  },
                  {
                    "type": "paragraph",
                    "text": "After creating the measure, format it as <strong>Percentage</strong>:"
                  },
                  {
                    "type": "steps",
                    "items": [
                      {
                        "title": "Select the measure in the Fields pane",
                        "description": "Click on YoY Growth % in the Fields panel on the right side of Power BI Desktop."
                      },
                      {
                        "title": "Go to Measure Tools → Format → Percentage",
                        "description": "In the top ribbon, under Measure Tools, change the format dropdown from General to Percentage. Set decimal places to 1 or 2."
                      }
                    ]
                  }
                ]
              },
              {
                "id": "visualize",
                "title": "Visualizing YoY Growth in a Chart",
                "content": [
                  {
                    "type": "paragraph",
                    "text": "A <strong>Clustered Bar Chart</strong> or <strong>Line and Clustered Column Chart</strong> works best for YoY comparisons. Here's a preview of what your final output should look like:"
                  },
                  {
                    "type": "subtitle",
                    "text": "How to Build This in Power BI"
                  },
                  {
                    "type": "steps",
                    "items": [
                      {
                        "title": "Insert a Line and Clustered Column Chart visual",
                        "description": "From the Visualizations pane, click the Line and Clustered Column Chart icon."
                      },
                      {
                        "title": "Set X-axis to Month Name from your Date Table",
                        "description": "Drag DateTable[MonthName] to the X-axis well. Make sure it's sorted by MonthNumber, not alphabetically."
                      },
                      {
                        "title": "Add Column Values and Line Value",
                        "description": "Drag Total Sales and PY Sales to Column Y-axis. Drag YoY Growth % to Line Y-axis."
                      },
                      {
                        "title": "Add a Year slicer",
                        "description": "Insert a Slicer visual and drag DateTable[Year] into it. This lets users dynamically select which year pair to compare."
                      }
                    ]
                  }
                ]
              },
              {
                "id": "comparison",
                "title": "Comparing All Three Methods",
                "content": [
                  {
                    "type": "table",
                    "title": "Comparison of DAX YoY Methods",
                    "headers": ["Function", "Best For", "Works With Partial Periods?", "Fiscal Year Support?", "Difficulty"],
                    "rows": [
                      ["SAMEPERIODLASTYEAR", "YoY — same period", "Yes", "Limited", "Easiest"],
                      ["DATEADD(-1, YEAR)", "YoY, QoQ, MoM", "Yes", "Yes", "Easy"],
                      ["PREVIOUSYEAR", "Full prior year total", "Returns full year", "Yes (date param)", "Easy"],
                      ["VAR with CALCULATE", "Complex logic, error handling", "Yes", "Yes", "Intermediate"]
                    ]
                  },
                  {
                    "type": "paragraph",
                    "text": "<strong>Our recommendation for beginners:</strong> Start with SAMEPERIODLASTYEAR. Once comfortable, migrate to the VAR-based pattern for production dashboards as it gives you full control over error handling and readability."
                  }
                ]
              },
              {
                "id": "tips",
                "title": "Pro Tips and Common Mistakes",
                "content": [
                  {
                    "type": "subtitle",
                    "text": "Best Practices"
                  },
                  {
                    "type": "list",
                    "items": [
                      "Always use DIVIDE() instead of the / operator — it handles divide-by-zero gracefully",
                      "Use VAR blocks for readability and to avoid recalculating measures multiple times",
                      "Format your YoY measure as Percentage from the Measure Tools tab",
                      "Add conditional formatting in table visuals to highlight positive (green) and negative (red) YoY values",
                      "Always mark your Date Table using Mark as Date Table in the right-click menu"
                    ]
                  },
                  {
                    "type": "subtitle",
                    "text": "Common Mistakes to Avoid"
                  },
                  {
                    "type": "list",
                    "items": [
                      "Mistake: Using a Date column from your fact table instead of a separate Date Table — Fix: Always create and use a dedicated Date Table with CALENDAR() or CALENDARAUTO()",
                      "Mistake: Date Table has gaps or missing dates — Fix: Use CALENDAR() with explicit start and end dates to ensure continuity",
                      "Mistake: YoY showing BLANK for recent months — Fix: This is expected if prior year data does not exist — use IF(ISBLANK()) to show N/A text instead",
                      "Mistake: Comparing calendar year when business uses fiscal year — Fix: Use the year-end-date parameter in PREVIOUSYEAR or DATESYTD"
                    ]
                  },
                  {
                    "type": "callout",
                    "variant": "tip",
                    "icon": "🏆",
                    "title": "Bonus Tip:",
                    "content": "Add a KPI Card visual with YoY Growth % as the value and set a target (e.g., 10%). Power BI will automatically show a green arrow (above target) or red arrow (below target) — perfect for executive dashboards!"
                  }
                ]
              },
              {
                "id": "faq",
                "title": "Frequently Asked Questions",
                "content": [
                  {
                    "type": "faq",
                    "items": [
                      {
                        "question": "What is the DAX formula for Year-over-Year growth in Power BI?",
                        "answer": "The most common DAX formula uses SAMEPERIODLASTYEAR inside a CALCULATE function. Create a PY Sales measure with CALCULATE([Total Sales], SAMEPERIODLASTYEAR(DateTable[Date])), then calculate growth % as DIVIDE([Total Sales] - [PY Sales], [PY Sales])."
                      },
                      {
                        "question": "What is the difference between SAMEPERIODLASTYEAR and PREVIOUSYEAR?",
                        "answer": "SAMEPERIODLASTYEAR returns the same date range from the prior year — if you have Jan-Jun 2024 selected, it returns Jan-Jun 2023. PREVIOUSYEAR always returns the entire previous year (Jan 1 to Dec 31), regardless of your current selection. Use SAMEPERIODLASTYEAR for period-to-period YoY comparisons and PREVIOUSYEAR for full-year totals."
                      },
                      {
                        "question": "Why is my YoY measure showing BLANK?",
                        "answer": "This usually happens when: (1) your Date Table is not marked as a Date Table, (2) there are gaps in your Date Table, (3) there is no data for the prior year period, or (4) the relationship between your fact table and Date Table is broken. Check all four of these first."
                      },
                      {
                        "question": "Can I calculate YoY for a Financial Year (April to March) in Power BI?",
                        "answer": "Yes! Use PREVIOUSYEAR(DateTable[Date], \"03-31\") for a fiscal year ending in March, or use DATEADD with custom fiscal year columns in your Date Table. You can also use DATESYTD([Date], \"03-31\") for Year-to-Date in fiscal year context."
                      },
                      {
                        "question": "Does YoY work with slicers in Power BI?",
                        "answer": "Yes — all three methods (SAMEPERIODLASTYEAR, DATEADD, PREVIOUSYEAR) work dynamically with slicers and cross-filtering as long as your Date Table is properly set up and marked. The measure automatically adjusts based on what the user selects."
                      }
                    ]
                  }
                ]
              }
            ],
            "troubleshooting": {
              "title": "Common Power BI YoY Issues",
              "subtitle": "Solutions to frequent problems when calculating Year-over-Year growth in Power BI",
              "cards": [
                {
                  "title": "YoY Showing BLANK",
                  "icon": "AlertCircle",
                  "color": "amber",
                  "content": "Check that your Date Table is marked as a Date Table, has no gaps, and has a valid relationship with your fact table."
                },
                {
                  "title": "Incorrect YoY Values",
                  "icon": "AlertTriangle",
                  "color": "red",
                  "content": "Ensure you are using DIVIDE() not the / operator. Check that the Date Table relationship is Many-to-One and active."
                },
                {
                  "title": "Slicers Not Working",
                  "icon": "Gauge",
                  "color": "blue",
                  "content": "Verify that cross-filter direction is set correctly in the relationship and the Date Table is properly marked."
                },
                {
                  "title": "Fiscal Year Mismatch",
                  "icon": "Calendar",
                  "color": "purple",
                  "content": "Use the year-end-date parameter in PREVIOUSYEAR or DATESYTD. Add fiscal year columns to your Date Table."
                },
                {
                  "title": "Performance Issues",
                  "icon": "Gauge",
                  "color": "pink",
                  "content": "Use VAR variables to avoid re-evaluating measures. Import mode is faster than DirectQuery for time intelligence."
                }
              ]
            },
            "conclusion": {
              "title": "Mastering YoY Growth in Power BI",
              "content": "You have now completed a comprehensive guide to calculating Year-over-Year growth in Power BI using DAX. From Date Table setup to three different methods and production-ready patterns, you are equipped to build professional-grade time intelligence dashboards.",
              "checklist": [
                { "item": "Set Up Date Table", "text": "Create with CALENDAR() and mark as Date Table" },
                { "item": "Choose Your Method", "text": "SAMEPERIODLASTYEAR for beginners, VAR pattern for production" },
                { "item": "Format Correctly", "text": "Set YoY measure format to Percentage in Measure Tools" },
                { "item": "Handle Edge Cases", "text": "Use DIVIDE() and IF(ISBLANK()) for robust formulas" },
                { "item": "Visualize Clearly", "text": "Line and Clustered Column Chart for YoY comparisons" },
                { "item": "Add KPI Cards", "text": "Highlight growth vs targets for executive dashboards" }
              ],
              "finalNote": "Remember: The goal is actionable insight, not just a formula. If your YoY chart does not make the business story clearer, simplify the visualization.",
              "finalParagraph": "By following this comprehensive guide, you will be able to create YoY growth dashboards that not only look professional but also drive meaningful business decisions. Start with SAMEPERIODLASTYEAR, gather feedback, and gradually tackle more complex time intelligence patterns."
            },
            "cta": {
              "title": "Ready to Master Power BI?",
              "content": "Join thousands of professionals who have transformed their careers with Ivy Professional School's hands-on Power BI and Data Analytics training programs.",
              "buttonText": "EXPLORE POWER BI COURSE"
            }
          }
        }
      ]
    },
    "tableau": {
      "title": "Tableau",
      "icon": "BarChart3",
      "color": "bg-pink-400",
      "topics": [
        {
          "id": "dual-axis-charts",
          "metaTitle": "Dual Axis Charts Explained | Data Visualization Guide",
          "title": "How to Create Dual-Axis Charts in Tableau: Complete Guide",
          "description": "Master dual-axis charts for business decision-making",
          "duration": "12 min read",
          "date": "March 15, 2026",
          "content": {
            "hero": {
              "title": "How to Create Dual-Axis Charts in Tableau: Complete Guide",
              "author": "Tableau Expert",
              "date": "March 15, 2026",
              "readTime": "12 min read"
            },
            "video": {
              "youtubeId": "U7dVFfE1wPw",
              "title": "Dual-Axis Charts in Tableau - Visual Guide"
            },
            "sections": [
              {
                "id": "intro",
                "title": "Introduction",
                "content": [
                  {
                    "type": "paragraph",
                    "text": "If you work with business data long enough, a stakeholder will eventually ask: \"Can we see both numbers together on one chart?\" This exact question is why dual-axis charts in Tableau exist.",
                    "hasBar": true
                  },
                  {
                    "type": "paragraph",
                    "text": "This guide assumes zero prior knowledge and gradually takes you to expert-level Tableau usage, covering not just how to create a dual-axis chart, but when, why, and when not to use it in real business dashboards."
                  }
                ]
              },
              {
                "id": "what-is",
                "title": "What Is a Dual-Axis Chart in Tableau?",
                "content": [
                  {
                    "type": "paragraph",
                    "text": "A dual-axis chart is a visualization where two different measures share the same X-axis (time, category, region) but have separate Y-axes, layered in a single view."
                  },
                  {
                    "type": "subtitle",
                    "text": "Key Components"
                  },
                  {
                    "type": "list",
                    "items": [
                      "One measure appears on the left Y-axis",
                      "The second measure appears on the right Y-axis",
                      "Both measures coexist on the same chart"
                    ]
                  }
                ]
              },
              {
                "id": "importance",
                "title": "Why Are Dual-Axis Charts Important for Business Decision-Making?",
                "content": [
                  {
                    "type": "paragraph",
                    "text": "Dual-axis charts are decision tools, not visual decoration. They help leaders answer questions like:"
                  },
                  {
                    "type": "list",
                    "items": [
                      "Are we growing profitably?",
                      "Is higher productivity affecting quality?",
                      "Is marketing driving meaningful conversions?",
                      "Is operational efficiency improving as teams scale?"
                    ]
                  },
                  {
                    "type": "paragraph",
                    "text": "Business leaders want: one view, one story, one actionable insight. A well-designed dual-axis chart compresses cause-and-effect relationships into a single visual narrative."
                  }
                ]
              },
              {
                "id": "when-to-use",
                "title": "When Should You Use a Dual-Axis Chart in Tableau?",
                "content": [
                  {
                    "type": "paragraph",
                    "text": "You should use a dual-axis chart only when all of the following are true:"
                  },
                  {
                    "type": "table",
                    "title": "Criteria for Using Dual-Axis Charts",
                    "headers": [
                      "Criteria",
                      "Example",
                      "Valid?"
                    ],
                    "rows": [
                      [
                        "Metrics are logically related",
                        "Sales & Profit Margin",
                        "✓"
                      ],
                      [
                        "Share same X-axis",
                        "Monthly timeline",
                        "✓"
                      ],
                      [
                        "Units are different",
                        "₹ vs %",
                        "✓"
                      ],
                      [
                        "Goal is trend comparison",
                        "Compare movement patterns",
                        "✓"
                      ]
                    ]
                  },
                  {
                    "type": "subtitle",
                    "text": "Real Business Examples"
                  },
                  {
                    "type": "list",
                    "items": [
                      "Monthly Sales vs Profit Margin",
                      "Daily Orders vs Average Delivery Time",
                      "Machine Output vs Defect Rate",
                      "Headcount vs Revenue per Employee"
                    ]
                  }
                ]
              },
              {
                "id": "when-not-to-use",
                "title": "When Should You Avoid Using a Dual-Axis Chart?",
                "content": [
                  {
                    "type": "paragraph",
                    "text": "Dual-axis charts should not be used when:"
                  },
                  {
                    "type": "table",
                    "title": "Anti-Patterns to Avoid",
                    "headers": [
                      "Situation",
                      "Example",
                      "Why to Avoid"
                    ],
                    "rows": [
                      [
                        "Unrelated metrics",
                        "Sales vs Employee Happiness",
                        "False correlation"
                      ],
                      [
                        "Manipulated axes",
                        "Scaled to look good",
                        "Misleading"
                      ],
                      [
                        "Hiding poor results",
                        "Hidden scale adjustments",
                        "Unethical"
                      ],
                      [
                        "Non-data-literate audience",
                        "Complex for beginners",
                        "Confusing"
                      ]
                    ]
                  },
                  {
                    "type": "warning",
                    "title": "Warning",
                    "content": "A misleading dual-axis chart damages trust faster than incorrect data."
                  }
                ]
              },
              {
                "id": "core-concepts",
                "title": "Core Tableau Concepts You Must Understand",
                "content": [
                  {
                    "type": "paragraph",
                    "text": "Before creating a dual-axis chart, you must understand three fundamentals:"
                  },
                  {
                    "type": "list",
                    "items": [
                      "Dimensions: These form the X-axis (Date, Month, Category, Region)",
                      "Measures: These form the Y-axes (Sales, Profit, Quantity, Rates)",
                      "Marks: These control how data is shown (Bar, Line, Area, Circle)"
                    ]
                  },
                  {
                    "type": "paragraph",
                    "text": "A dual-axis chart simply means two measures, two axes, one shared dimension."
                  }
                ]
              },
              {
                "id": "basic-chart",
                "title": "How Do You Create a Basic Chart in Tableau?",
                "phase": "Step 1: Foundation",
                "content": [
                  {
                    "type": "paragraph",
                    "text": "Start with a simple chart:"
                  },
                  {
                    "type": "code",
                    "title": "Basic Chart Setup",
                    "language": "tableau",
                    "code": "1. Drag a time-based dimension (Order Date) to Columns\n2. Drag a measure (Sales) to Rows\n\nResult: Basic line chart showing sales over time",
                    "borderColor": "pink"
                  },
                  {
                    "type": "paragraph",
                    "text": "This creates your base visualization, which will later become the foundation for the dual-axis chart."
                  }
                ]
              },
              {
                "id": "add-second-measure",
                "title": "How Do You Add a Second Measure?",
                "phase": "Step 2: Add Companion Metric",
                "content": [
                  {
                    "type": "paragraph",
                    "text": "To introduce the second metric:"
                  },
                  {
                    "type": "code",
                    "title": "Add Second Measure",
                    "language": "tableau",
                    "code": "Drag the second measure (Profit) to Rows\n\nTableau displays two separate charts stacked vertically.\nAt this stage, this is NOT a dual-axis chart.",
                    "borderColor": "pink"
                  }
                ]
              },
              {
                "id": "convert-dual-axis",
                "title": "How Do You Convert to Dual-Axis Chart?",
                "phase": "Step 3: The Magic Transformation",
                "content": [
                  {
                    "type": "paragraph",
                    "text": "To convert the view into a dual-axis chart:"
                  },
                  {
                    "type": "code",
                    "title": "Dual-Axis Activation",
                    "language": "tableau",
                    "code": "1. Right-click on the second Y-axis\n2. Select 'Dual Axis'\n\nTableau now layers both measures in a single view and displays:\n- A left Y-axis\n- A right Y-axis\n- Separate Marks cards for each measure",
                    "borderColor": "pink"
                  }
                ]
              },
              {
                "id": "synchronize-axes",
                "title": "Should You Synchronize Axes?",
                "content": [
                  {
                    "type": "paragraph",
                    "text": "You should synchronize axes only when both measures use the same unit."
                  },
                  {
                    "type": "table",
                    "title": "Synchronization Decision Guide",
                    "headers": [
                      "Situation",
                      "Units",
                      "Synchronize?"
                    ],
                    "rows": [
                      [
                        "Sales & Profit",
                        "Both in ₹",
                        "✓ Yes"
                      ],
                      [
                        "Sales (₹) & Margin (%)",
                        "₹ vs %",
                        "✗ No"
                      ],
                      [
                        "Quantity & Units",
                        "Count vs Count",
                        "✓ Yes"
                      ],
                      [
                        "Time & Percentage",
                        "Days vs %",
                        "✗ No"
                      ]
                    ]
                  },
                  {
                    "type": "warning",
                    "title": "Critical Warning",
                    "content": "Synchronizing mismatched units creates misleading visuals and should be avoided."
                  }
                ]
              },
              {
                "id": "mark-types",
                "title": "How Do You Choose the Right Mark Types?",
                "content": [
                  {
                    "type": "paragraph",
                    "text": "The choice of marks determines readability. Best practice combinations include:"
                  },
                  {
                    "type": "table",
                    "title": "Recommended Mark Combinations",
                    "headers": [
                      "Primary Metric",
                      "Secondary Metric",
                      "Visual Style",
                      "Use Case"
                    ],
                    "rows": [
                      [
                        "Sales (Volume)",
                        "Profit Margin",
                        "Bars + Line",
                        "Revenue vs Efficiency"
                      ],
                      [
                        "Orders",
                        "Avg Delivery Time",
                        "Area + Line",
                        "Volume vs Speed"
                      ],
                      [
                        "Website Traffic",
                        "Conversion Rate",
                        "Line + Circle",
                        "Volume vs Quality"
                      ],
                      [
                        "Production Output",
                        "Defect Rate",
                        "Bars + Line",
                        "Quantity vs Quality"
                      ]
                    ]
                  },
                  {
                    "type": "paragraph",
                    "text": "A common business pattern is: Volume-based metric as Bars, Efficiency-based metric as Line. This visually separates magnitude from performance quality."
                  }
                ]
              },
              {
                "id": "formatting",
                "title": "How Should You Format Dual-Axis Charts for Clarity?",
                "content": [
                  {
                    "type": "paragraph",
                    "text": "Formatting determines whether a dual-axis chart builds trust or confusion."
                  },
                  {
                    "type": "checklist",
                    "items": [
                      {
                        "checked": true,
                        "text": "Clearly label both Y-axes"
                      },
                      {
                        "checked": true,
                        "text": "Always include units (₹, %, days)"
                      },
                      {
                        "checked": true,
                        "text": "Use distinct but restrained colors"
                      },
                      {
                        "checked": true,
                        "text": "Customize tooltips for each measure"
                      }
                    ]
                  },
                  {
                    "type": "warning",
                    "title": "Remember",
                    "content": "A dual-axis chart without clear labels is functionally useless."
                  }
                ]
              },
              {
                "id": "sales-profit-analysis",
                "title": "Sales vs Profit Margin Analysis",
                "phase": "Business Application 1",
                "content": [
                  {
                    "type": "paragraph",
                    "text": "This chart answers the question: Are we growing profitably?"
                  },
                  {
                    "type": "table",
                    "title": "Pattern Recognition Guide",
                    "headers": [
                      "Sales Trend",
                      "Margin Trend",
                      "Business Insight",
                      "Action Required"
                    ],
                    "rows": [
                      [
                        "↑ Increasing",
                        "↓ Decreasing",
                        "Excessive discounting",
                        "Review pricing strategy"
                      ],
                      [
                        "→ Stable",
                        "↑ Increasing",
                        "Cost optimization",
                        "Scale successful practices"
                      ],
                      [
                        "↑ Increasing",
                        "↑ Increasing",
                        "Healthy growth",
                        "Continue current strategy"
                      ],
                      [
                        "↓ Decreasing",
                        "↓ Decreasing",
                        "Market pressure",
                        "Strategic review needed"
                      ]
                    ]
                  },
                  {
                    "type": "paragraph",
                    "text": "This insight often drives pricing, discount, and incentive decisions."
                  }
                ]
              },
              {
                "id": "marketing-effectiveness",
                "title": "Marketing: Traffic vs Conversion Rate",
                "phase": "Business Application 2",
                "content": [
                  {
                    "type": "paragraph",
                    "text": "This chart answers: Is marketing driving quality traffic?"
                  },
                  {
                    "type": "table",
                    "title": "Marketing Insights Matrix",
                    "headers": [
                      "Traffic",
                      "Conversion",
                      "Insight",
                      "Team Action"
                    ],
                    "rows": [
                      [
                        "↑ Spikes",
                        "↓ Drops",
                        "Poor targeting",
                        "Refine audience segmentation"
                      ],
                      [
                        "→ Stable",
                        "↑ Rises",
                        "Funnel improvement",
                        "Optimize landing pages"
                      ],
                      [
                        "↑ Increases",
                        "↑ Increases",
                        "Effective campaigns",
                        "Increase budget"
                      ],
                      [
                        "↓ Declines",
                        "→ Stable",
                        "Channel fatigue",
                        "Explore new channels"
                      ]
                    ]
                  },
                  {
                    "type": "paragraph",
                    "text": "This is a critical view for growth and product teams."
                  }
                ]
              },
              {
                "id": "manufacturing-quality",
                "title": "Manufacturing: Output vs Defect Rate",
                "phase": "Business Application 3",
                "content": [
                  {
                    "type": "paragraph",
                    "text": "This chart answers: Is higher output hurting quality?"
                  },
                  {
                    "type": "table",
                    "title": "Quality Control Patterns",
                    "headers": [
                      "Output",
                      "Defects",
                      "Diagnosis",
                      "Corrective Action"
                    ],
                    "rows": [
                      [
                        "↑ Up",
                        "↑ Up",
                        "Process stress",
                        "Reduce speed, add QC checkpoints"
                      ],
                      [
                        "↑ Up",
                        "↓ Down",
                        "Process maturity",
                        "Document best practices"
                      ],
                      [
                        "↓ Down",
                        "↑ Up",
                        "Systemic failure",
                        "Root cause analysis"
                      ],
                      [
                        "→ Stable",
                        "↓ Down",
                        "Continuous improvement",
                        "Share learnings"
                      ]
                    ]
                  },
                  {
                    "type": "paragraph",
                    "text": "These patterns often trigger audits and root-cause analysis."
                  }
                ]
              },
              {
                "id": "hr-productivity",
                "title": "HR Analytics: Headcount vs Revenue per Employee",
                "phase": "Business Application 4",
                "content": [
                  {
                    "type": "paragraph",
                    "text": "This chart answers: Is hiring improving efficiency?"
                  },
                  {
                    "type": "table",
                    "title": "HR Productivity Analysis",
                    "headers": [
                      "Headcount",
                      "Revenue/Employee",
                      "Interpretation",
                      "Strategic Decision"
                    ],
                    "rows": [
                      [
                        "↑ Increasing",
                        "↓ Decreasing",
                        "Over-hiring",
                        "Freeze hiring, training focus"
                      ],
                      [
                        "→ Stable",
                        "↑ Increasing",
                        "Productivity gains",
                        "Reward programs, automation"
                      ],
                      [
                        "↓ Decreasing",
                        "↑ Increasing",
                        "Right-sizing",
                        "Continue optimization"
                      ],
                      [
                        "↑ Increasing",
                        "↑ Increasing",
                        "Scalable growth",
                        "Strategic expansion"
                      ]
                    ]
                  },
                  {
                    "type": "paragraph",
                    "text": "This view directly influences hiring plans and automation decisions."
                  }
                ]
              },
              {
                "id": "calculated-fields",
                "title": "How to Use Calculated Fields",
                "phase": "Advanced Technique 1",
                "content": [
                  {
                    "type": "paragraph",
                    "text": "Advanced users rely on calculated fields rather than raw data."
                  },
                  {
                    "type": "code",
                    "title": "Profit Margin Calculation",
                    "language": "tableau",
                    "code": "// CALCULATED FIELD: Profit Margin\nSUM([Profit]) / SUM([Sales])\n\n// FORMAT AS PERCENTAGE\nNumber Format: Percentage (1 decimal)\n\n// ADVANTAGES:\n// - Correct aggregation\n// - Consistent logic\n// - Reduced reporting errors",
                    "borderColor": "purple"
                  }
                ]
              },
              {
                "id": "reference-lines",
                "title": "How Reference Lines Improve Charts",
                "phase": "Advanced Technique 2",
                "content": [
                  {
                    "type": "paragraph",
                    "text": "Reference lines add business context such as targets, SLAs, or compliance thresholds."
                  },
                  {
                    "type": "code",
                    "title": "Adding Reference Lines",
                    "language": "tableau",
                    "code": "// ADD REFERENCE LINE\nRight-click Y-axis → Add Reference Line\n\n// TYPES:\nLine: Constant value (e.g., 20% margin target)\nBand: Range (e.g., 15-25% acceptable range)\nDistribution: Statistical (e.g., average, median)\n\n// WITHOUT BENCHMARKS, TRENDS LACK MEANING",
                    "borderColor": "blue"
                  }
                ]
              },
              {
                "id": "parameters",
                "title": "How Parameters Make Charts Interactive",
                "phase": "Advanced Technique 3",
                "content": [
                  {
                    "type": "paragraph",
                    "text": "Parameters allow users to switch metrics dynamically without cluttering the dashboard."
                  },
                  {
                    "type": "code",
                    "title": "Dynamic Metric Selection",
                    "language": "tableau",
                    "code": "// CREATE PARAMETER\nParameter Name: [Select Secondary Metric]\nData Type: String\nList Values:\n- Profit Margin\n- Conversion Rate\n- Defect Rate\n- Revenue per Employee\n\n// USE IN CALCULATION\nCASE [Select Secondary Metric]\n  WHEN \"Profit Margin\" THEN SUM([Profit])/SUM([Sales])\n  WHEN \"Conversion Rate\" THEN SUM([Conversions])/SUM([Visits])\n  ...\nEND",
                    "borderColor": "amber"
                  },
                  {
                    "type": "paragraph",
                    "text": "This transforms a static chart into an analytical tool."
                  }
                ]
              },
              {
                "id": "decision-guide",
                "title": "Dual-Axis vs Separate Charts",
                "content": [
                  {
                    "type": "table",
                    "title": "Architecture Decision Matrix",
                    "headers": [
                      "Situation",
                      "Use Dual-Axis",
                      "Use Separate Charts",
                      "Rationale"
                    ],
                    "rows": [
                      [
                        "Relationship analysis",
                        "✓ Yes",
                        "✗ No",
                        "Understanding connection is primary goal"
                      ],
                      [
                        "Detailed inspection",
                        "✗ No",
                        "✓ Yes",
                        "Each metric needs individual focus"
                      ],
                      [
                        "Executive summary",
                        "✓ Yes",
                        "✗ No",
                        "High-level relationship view"
                      ],
                      [
                        "Technical deep dive",
                        "✗ No",
                        "✓ Yes",
                        "Precision over synthesis"
                      ],
                      [
                        "Dashboard space limited",
                        "✓ Carefully",
                        "✓ If possible",
                        "Dual-axis saves space but risks clarity"
                      ]
                    ]
                  },
                  {
                    "type": "warning",
                    "title": "Dashboard Design Warning",
                    "content": "A dashboard overloaded with dual-axis charts is a warning sign of poor information architecture."
                  }
                ]
              },
              {
                "id": "misinterpretations",
                "title": "Common Executive Misinterpretations",
                "content": [
                  {
                    "type": "paragraph",
                    "text": "Executives may incorrectly assume:"
                  },
                  {
                    "type": "list",
                    "items": [
                      "Both axes are comparable (they're often not)",
                      "Line crossings imply correlation (correlation ≠ causation)",
                      "The right axis is secondary (both are equally important)",
                      "Scale differences indicate problems (sometimes they're just different units)"
                    ]
                  },
                  {
                    "type": "subtitle",
                    "text": "Prevention Strategies"
                  },
                  {
                    "type": "checklist",
                    "items": [
                      {
                        "checked": true,
                        "text": "Explicit axis labeling with units"
                      },
                      {
                        "checked": true,
                        "text": "Annotations explaining relationships"
                      },
                      {
                        "checked": true,
                        "text": "Short explanatory captions"
                      },
                      {
                        "checked": true,
                        "text": "Pre-meeting walkthrough for complex charts"
                      }
                    ]
                  }
                ]
              },
              {
                "id": "pre-publish-checklist",
                "title": "Pre-Publication Checklist",
                "phase": "Quality Assurance",
                "content": [
                  {
                    "type": "checklist",
                    "items": [
                      {
                        "checked": true,
                        "text": "Metrics are logically related"
                      },
                      {
                        "checked": true,
                        "text": "Axes are clearly labeled with units"
                      },
                      {
                        "checked": true,
                        "text": "Scales are not manipulated"
                      },
                      {
                        "checked": true,
                        "text": "Business question is obvious"
                      },
                      {
                        "checked": true,
                        "text": "Chart can survive boardroom challenge"
                      },
                      {
                        "checked": true,
                        "text": "Color scheme is accessible (colorblind friendly)"
                      },
                      {
                        "checked": true,
                        "text": "Tooltips provide useful information"
                      }
                    ]
                  },
                  {
                    "type": "quote",
                    "text": "If your chart doesn't pass this checklist, redesign it. A flawed visualization is worse than no visualization."
                  }
                ]
              },
              {
                "id": "power-vs-risk",
                "title": "The Power vs Risk Balance",
                "content": [
                  {
                    "type": "analogy",
                    "title": "The Surgeon's Scalpel Analogy",
                    "icon": "Scissors",
                    "color": "red",
                    "content": {
                      "main": "Dual-axis charts are like surgical instruments in the hands of a data analyst.",
                      "cards": [
                        {
                          "title": "In Expert Hands:",
                          "content": "Reveal hidden relationships, reduce cognitive load, drive better decisions",
                          "color": "emerald-600"
                        },
                        {
                          "title": "In Novice Hands:",
                          "content": "Mislead stakeholders, manipulate perception, destroy credibility",
                          "color": "red-600"
                        }
                      ]
                    }
                  },
                  {
                    "type": "paragraph",
                    "text": "Dual-axis charts are like sharp tools. Used correctly, they reveal hidden relationships, reduce cognitive load, and drive better decisions. Used poorly, they mislead stakeholders, manipulate perception, and destroy credibility. Master them responsibly."
                  }
                ]
              }
            ],
            "troubleshooting": {
              "title": "Common Tableau Dual-Axis Issues",
              "subtitle": "Solutions to frequent problems encountered when creating dual-axis charts",
              "cards": [
                {
                  "title": "Misaligned Axes",
                  "icon": "AlignLeft",
                  "color": "amber",
                  "content": "Right-click axis → Synchronize Axis. Only use when metrics share same unit of measure."
                },
                {
                  "title": "Overlapping Marks",
                  "icon": "Layers",
                  "color": "pink",
                  "content": "Adjust transparency in Marks card. Use different mark types (bars + lines work well together)."
                },
                {
                  "title": "Unreadable Tooltips",
                  "icon": "MessageCircle",
                  "color": "blue",
                  "content": "Customize tooltips separately for each measure. Include units and clear descriptions."
                },
                {
                  "title": "Color Confusion",
                  "icon": "Palette",
                  "color": "purple",
                  "content": "Use colorblind-friendly palettes. Ensure sufficient contrast between series."
                },
                {
                  "title": "Performance Issues",
                  "icon": "Gauge",
                  "color": "red",
                  "content": "Limit data volume. Use extracts instead of live connections. Simplify calculations."
                }
              ]
            },
            "conclusion": {
              "title": "Mastering Dual-Axis Charts",
              "content": "You have now completed a comprehensive guide to creating dual-axis charts in Tableau. From basic setup to advanced techniques, you've learned not just how to create these charts, but when, why, and when not to use them.",
              "checklist": [
                {
                  "item": "Start Simple",
                  "text": "Master basic charts before attempting dual-axis"
                },
                {
                  "item": "Validate Relationship",
                  "text": "Ensure metrics are logically connected"
                },
                {
                  "item": "Format Professionally",
                  "text": "Clear labels, appropriate colors, useful tooltips"
                },
                {
                  "item": "Test Interpretations",
                  "text": "Verify stakeholders understand the chart correctly"
                },
                {
                  "item": "Have Backup",
                  "text": "Keep single-chart versions available"
                },
                {
                  "item": "Document Decisions",
                  "text": "Note why dual-axis was chosen over alternatives"
                }
              ],
              "finalNote": "Remember: The goal is insight, not just visualization. If a dual-axis chart doesn't make the business story clearer, use a different approach.",
              "finalParagraph": "By following this comprehensive guide, you'll be able to create dual-axis charts that not only look professional but also drive meaningful business decisions. Start with simple applications, gather feedback, and gradually tackle more complex analytical challenges."
            },
            "cta": {
              "title": "Ready to Master Tableau Visualization?",
              "content": "Download our Tableau dual-axis chart template with sample datasets and step-by-step exercises.",
              "buttonText": "GET TABLEAU TEMPLATE PACK"
            }
          }
        }
      ]
    }
  }
}